hyperfoil/__init__.py
hyperfoil/client.py
hyperfoil/clients.py
hyperfoil/defaults.py
hyperfoil/errors.py
hyperfoil/resources.py
hyperfoil/utils.py
hyperfoil/factories/__init__.py
hyperfoil/factories/benchmark.py
hyperfoil/factories/benchmark_factory.py
hyperfoil/factories/hyperfoil_factory.py
tests/factories/__init__.py
tests/factories/hyperfoil_factory_test.py
hyperfoil_client-0.1.8.dist-info/METADATA
hyperfoil_client-0.1.8.dist-info/WHEEL
hyperfoil_client-0.1.8.dist-info/top_level.txt
hyperfoil_client-0.1.8.dist-info/RECORD
