Metadata-Version: 2.1
Name: hyperfoil-client
Version: 0.1.8
Summary: Hyperfoil python client
Home-page: https://github.com/jsmadis/hyperfoil-python-client
Author: Jakub Smadis
Author-email: jakub.smadis@gmail.com
Maintainer: Jakub Smadis
License: UNKNOWN
Platform: UNKNOWN
Classifier: Development Status :: 2 - Pre-Alpha
Classifier: Topic :: Utilities
Classifier: Operating System :: OS Independent
Classifier: License :: OSI Approved :: Apache Software License
Classifier: Intended Audience :: Developers
Classifier: Programming Language :: Python :: 3
Classifier: Programming Language :: Python :: 3.8
Requires-Dist: requests
Requires-Dist: pyyaml
Provides-Extra: dev
Requires-Dist: pytest ; extra == 'dev'
Requires-Dist: python-dotenv ; extra == 'dev'
Provides-Extra: docs
Requires-Dist: sphinx ; extra == 'docs'
